README.md
main.py
setup.py
BithumbGlobal/__init__.py
bithumb_bot.egg-info/PKG-INFO
bithumb_bot.egg-info/SOURCES.txt
bithumb_bot.egg-info/dependency_links.txt
bithumb_bot.egg-info/entry_points.txt
bithumb_bot.egg-info/top_level.txt
prettyoutput/__init__.py
strategy/__init__.py
strategy/bithumb.py
strategy/first.py
strategy/second.py