Metadata-Version: 1.0
Name: bithumb-bot
Version: 0.13.1
Summary: auto trading bot bithumb
Home-page: https://github.com/bonsai-minter/bithumb-bot
Author: commaster
Author-email: admin@mcorp.space
License: Copyright [2020] [commaster] Licensed under the Apache License, Version 2.0 (the «License»);
Platform: UNKNOWN
